varbert/__init__.py
varbert/__main__.py
varbert/api.py
varbert/logger.py
varbert/model.py
varbert/text_processor.py
varbert/models/__init__.py
varbert-2.3.0.dist-info/LICENSE
varbert-2.3.0.dist-info/METADATA
varbert-2.3.0.dist-info/WHEEL
varbert-2.3.0.dist-info/entry_points.txt
varbert-2.3.0.dist-info/top_level.txt
varbert-2.3.0.dist-info/RECORD
