Metadata-Version: 2.1
Name: varbert
Version: 2.3.0
Summary: The VarBERT API for renaming variables in decompiled code.
Home-page: https://github.com/binsync/varbert_api
License: BSD 2 Clause
Classifier: License :: OSI Approved :: BSD License
Classifier: Programming Language :: Python :: 3
Classifier: Programming Language :: Python :: 3.6
Requires-Python: >=3.8
License-File: LICENSE
Requires-Dist: torch
Requires-Dist: transformers
Requires-Dist: tqdm
Requires-Dist: dailalib
Requires-Dist: libbs >=1.18.1
